dip_toolkit/__init__.py
dip_toolkit/doc_tools.py
quetzal_ai_toolkit-0.0.2.dist-info/LICENCE
quetzal_ai_toolkit-0.0.2.dist-info/METADATA
quetzal_ai_toolkit-0.0.2.dist-info/WHEEL
quetzal_ai_toolkit-0.0.2.dist-info/top_level.txt
quetzal_ai_toolkit-0.0.2.dist-info/RECORD
