Metadata-Version: 2.1
Name: quetzal-ai-toolkit
Version: 0.0.2
Summary: An AI utility
Home-page: https://github.com/mukulbindal/quetzal_ai_toolkit
Author: old_quetzal
Author-email: mukulbindal170299@gmail.com
Project-URL: Bug Tracker, https://github.com/mukulbindal/quetzal_ai_toolkit/issues
Classifier: Programming Language :: Python :: 3
Classifier: License :: OSI Approved :: MIT License
Classifier: Operating System :: OS Independent
Requires-Python: >=3.6
License-File: LICENCE
Requires-Dist: opencv-python
Requires-Dist: numpy
